setup.py
hksadipkg/__init__.py
hksadipkg/calculator.py
hksadipkg.egg-info/PKG-INFO
hksadipkg.egg-info/SOURCES.txt
hksadipkg.egg-info/dependency_links.txt
hksadipkg.egg-info/top_level.txt