Metadata-Version: 2.1
Name: hksadipkg
Version: 0.0.1
Summary: ADI python Package module
Home-page: https://github.com/hkshitesh/mydemopackage
Author: hiteshupes
Author-email: hiteshupes@gmail.com
Classifier: Programming Language :: Python :: 3
Classifier: Operating System :: OS Independent
